kda/__init__.py
kda/_version.py
kda/calculations.py
kda/diagrams.py
kda/exceptions.py
kda/expressions.py
kda/graph_utils.py
kda/ode.py
kda/plotting.py
kda/svd.py
kda/data/README.md
kda/data/look_and_say.dat
kda/scripts/README.md
kda/scripts/consolidate_data.py
kda/scripts/rmsd.py
kda/scripts/run_verification.py
kda/scripts/timing.py
kda/scripts/verification.py
kda/tests/__init__.py
kda/tests/test_kda.py
kda/tests/test_plotting.py
kda-0.3.0.dist-info/LICENSE
kda-0.3.0.dist-info/METADATA
kda-0.3.0.dist-info/WHEEL
kda-0.3.0.dist-info/top_level.txt
kda-0.3.0.dist-info/RECORD
