Metadata-Version: 2.1
Name: kda
Version: 0.3.0
Summary: Kinetic Diagram Analysis tools
Home-page: https://github.com/Becksteinlab/kda/
Author: Nikolaus Awtrey
Author-email: nawtrey@asu.edu
License: LGPLv3
Project-URL: Source, https://github.com/Becksteinlab/kda/
Project-URL: Issue Tracker, https://github.com/Becksteinlab/kda/issues
Keywords: science kinetics chemistry physics
License-File: LICENSE
Requires-Dist: numpy
Requires-Dist: networkx
Requires-Dist: scipy
Requires-Dist: sympy
Requires-Dist: matplotlib
